dbrownell_uvtest/Lib.py
dbrownell_uvtest/__init__.py
dbrownell_uvtest/main.py
dbrownell_uvtest-1.2.3.dist-info/METADATA
dbrownell_uvtest-1.2.3.dist-info/WHEEL
dbrownell_uvtest-1.2.3.dist-info/entry_points.txt
dbrownell_uvtest-1.2.3.dist-info/RECORD
