Metadata-Version: 2.4
Name: dbrownell-uvtest
Version: 1.2.3
Summary: Add your description here
Author-email: David Brownell <github@davidbrownell.com>
Requires-Python: >=3.13
Requires-Dist: typer>=0.15.1
